pseudo_cron/__init__.py
pseudo_cron/admin.py
pseudo_cron/decorators.py
pseudo_cron/middleware.py
pseudo_cron/models.py
pseudo_cron/utils.py
pseudo_cron/version.py
pseudo_cron/migrations/0001_initial.py
pseudo_cron/migrations/__init__.py
pseudo_cron/service/__init__.py
pseudo_cron/service/factory.py
pseudo_cron/service/models.py
pseudo_cron/service/service.py
pseudo_cron-1.0.4.dist-info/METADATA
pseudo_cron-1.0.4.dist-info/WHEEL
pseudo_cron-1.0.4.dist-info/top_level.txt
pseudo_cron-1.0.4.dist-info/RECORD
