Metadata-Version: 2.1
Name: pseudo-cron
Version: 1.0.4
Summary: Pseudo cron for Django
Home-page: https://github.com/bboogaard/pseudo_cron
Author: Bram Boogaard
Author-email: padawan@hetnet.nl
License: MIT License
Keywords: Django cron
Classifier: Development Status :: 3 - Alpha
Requires-Dist: pytest
Requires-Dist: pytest-cov
Requires-Dist: pytest-django ==4.5.2
Requires-Dist: django ==3.2.23
